stc8usb/stc8usb.py
stc8usb-0.2.1.dist-info/LICENSE
stc8usb-0.2.1.dist-info/METADATA
stc8usb-0.2.1.dist-info/WHEEL
stc8usb-0.2.1.dist-info/entry_points.txt
stc8usb-0.2.1.dist-info/top_level.txt
stc8usb-0.2.1.dist-info/RECORD
